[
  {
    "title": "Lyra",
    "description": "Lyra is a SFW Requiem modlist with a cozy and warm fantasy vibe; emphasizing exploration, challenge and fun! Built with Requiem Lite in mind. \u2764\uFE0F \u2014 Powered by Wabbajack.",
    "author": "iyreshot",
    "maintainers": [
      "github/iyreshot"
    ],
    "game": "skyrimspecialedition",
    "official": false,
    "tags": [
      "SFW",
      "Steam",
      "Requiem"
    ],
    "nsfw": false,
    "utility_list": false,
    "image_contains_title": true,
    "DisplayVersionOnlyInInstallerView": false,
    "force_down": false,
    "links": {
      "image": "https://raw.githubusercontent.com/iyreshot/Modlist/main/logo.png",
      "readme": "https://github.com/iyreshot/Modlist",
      "download": "https://authored-files.wabbajack.org/Lyra.wabbajack_7950d378-320c-4aa7-9aa0-6cb2eba8377e",
      "machineURL": "LyraRequiemWabba",
      "discordURL": "https://discord.com/invite/QBcggWVJwS",
      "websiteURL": ""
    },
    "download_metadata": {
      "Hash": "WOzAKFhG7tQ=",
      "Size": 277386316,
      "NumberOfArchives": 1553,
      "SizeOfArchives": 129990661136,
      "NumberOfInstalledFiles": 180920,
      "SizeOfInstalledFiles": 198677518435,
      "TotalSize": 328668179571
    },
    "version": "0.4.0",
    "dateCreated": "1970-01-01T00:00:00Z",
    "dateUpdated": "2026-02-10T17:13:11.1390774Z",
    "repositoryName": ""
  }
]